searchlib/__init__.py
searchlib/algorithms.py
searchlib/beam.py
searchlib/bidirectional.py
searchlib/display.py
searchlib/eda.py
searchlib/modeleval.py
searchlib/plots.py
searchlib/sentiment.py
searchlib/supervised.py
searchlib/unsupervised.py
searchlib_for_a_grade-1.1.1.dist-info/METADATA
searchlib_for_a_grade-1.1.1.dist-info/WHEEL
searchlib_for_a_grade-1.1.1.dist-info/top_level.txt
searchlib_for_a_grade-1.1.1.dist-info/RECORD
