Metadata-Version: 2.4
Name: searchlib_for_A_grade
Version: 1.1.1
Summary: A library to retrieve AI algorithm code snippets
Author: Khizer ALi
Dynamic: author
Dynamic: summary
